{
    "type": "news-item",
    "id": "642401F08A5434FEB565712A",
    "attributes": {
        "title": "Subsidie projectoproep circulair water",
        "alternativeTitle": null,
        "htmlContent": "<p>De Vlaamse Regering <strong>keurt de oproep 'circulair water' 2023 en het subsidiereglement daarvoor goed,</strong> om de waterbeschikbaarheid in Vlaanderen te vergroten en circulair watergebruik op te schalen. Vlaanderen is immers kwetsbaar voor droogte en waterschaarste, en werd de voorbije 6 jaar 5 keer getroffen door droogte. De projectoproep steunt samenwerkingen die <strong>focussen op minder waterverbruik en meer circulair watergebruik</strong>, zoals uitwisseling van waterstromen, hergebruik van effluent of de ontwikkeling van innovatieve technieken die primaire waterbronnen beschermen en aanvullen. Voor de oproep is een budget van <strong>10 miljoen euro</strong> voorzien in het kader van de uitgaven voor de Blue Deal, ter realisatie van het Vlaams Klimaatadaptatieplan. </p>",
        "position": 30,
        "mandateeNames": null,
        "mandateeFirstNames": "Zuhal",
        "mandateeFamilyNames": "Demir",
        "mandateeIds": "aa642a1e-7cc4-44da-9a6b-bce625761c5f",
        "mandateeTitles": "Vlaams minister van Justitie en Handhaving, Omgeving, Energie en Toerisme",
        "meetingDate": "2023-03-31T08:00:00Z",
        "meetingId": "6421A81A3335D329E25EDD30",
        "meetingTypePosition": 4,
        "themeId": [
            "758c3c7d-5b60-4eff-9320-2431a3120d19",
            "97028dc8-9a4a-466f-a9b9-244bae08221e"
        ],
        "agendaitemType": "Nota",
        "uuid": "642401F08A5434FEB565712A",
        "uri": "http://themis.vlaanderen.be/id/nieuwsbericht/642401F08A5434FEB565712A"
    }
}