{
    "type": "news-item",
    "id": "62722FB91C4A193816C30632",
    "attributes": {
        "title": "Verplicht inburgeringstraject voor nieuwkomers in Brussel-Hoofdstad: gewijzigde samenwerkingsovereenkomst",
        "alternativeTitle": "A. Ontwerp van samenwerkingsakkoord van XX X 2022 tot wijziging van het samenwerkingsakkoord van 20 december 2018 tussen de Vlaamse Gemeenschap, de Franse Gemeenschapscommissie en de Gemeenschappelijke Gemeenschapscommissie met betrekking tot het verplicht inburgeringstraject voor de nieuwkomers in Brussel-Hoofdstad\nB. Ontwerp van instemmingsdecreet",
        "htmlContent": "De Vlaamse Regering hecht&nbsp;<strong>\u200b</strong>haar&nbsp;<strong>definitieve goedkeuring</strong>&nbsp;aan <strong>het gewijzigde samenwerkingsakkoord t</strong><strong>ussen de Vlaamse Gemeenschap, de Franse Gemeenschapscommissie en de Gemeenschappelijke Gemeenschapscommissie met betrekking tot het verplicht inburgeringstraject voor nieuwkomers in Brussel-Hoofdstad</strong>. De wijziging omvat de&nbsp;<strong>invoeging van&nbsp;</strong><strong>een</strong>&nbsp;<strong>wettelijke basis voor de verwerking van persoonsgegevens in een uniform computergestuurd systeem</strong>. Dit uniform computergestuurd systeem zal gebruikt worden voor de opvolging van de dossiers van nieuwkomers en zal ter beschikking worden gesteld van de gemeenten van het tweetalige gebied Brussel-Hoofdstad, de erkende inrichters van het inburgeringstraject en de nieuwkomers.",
        "position": 14,
        "mandateeNames": null,
        "mandateeFirstNames": "Bart",
        "mandateeFamilyNames": "Somers",
        "mandateeIds": "1e207740-3834-4e98-8431-5a2c08704516",
        "mandateeTitles": "Vlaams minister van Binnenlands Bestuur, Bestuurszaken, Inburgering en Gelijke Kansen",
        "meetingDate": "2022-05-06T08:00:00Z",
        "meetingId": "626FC5421C4A193816C3017F",
        "meetingTypePosition": 4,
        "themeId": [
            "4dfb835d-ded2-4298-85bb-ff41f3563193",
            "34394a01-5c8c-44c9-aade-59087026f266"
        ],
        "agendaitemType": "Nota",
        "uuid": "62722FB91C4A193816C30632",
        "uri": "http://themis.vlaanderen.be/id/nieuwsbrief-info/62722FB91C4A193816C30632"
    }
}