{
    "type": "news-item",
    "id": "5EF1ADDBAD26920008000518",
    "attributes": {
        "title": "Beleidsprioriteiten bovenlokale cultuurwerking",
        "alternativeTitle": null,
        "htmlContent": "                            <!---->\n\n Het Bovenlokaal Cultuurdecreet bepaalt dat de Vlaamse Regering  voor 30 juni van het eerste volledige jaar van elke nieuwe legislatuur van het Vlaams Parlement, de beleidsprioriteiten voor de bovenlokale cultuurwerking bekendmaakt. De beleidsprioriteiten zijn toetsstenen voor de bovenlokale cultuurprojecten. <strong>De Vlaamse Regering keurt nu principieel het voorstel van beleidsprioriteiten goed voor de bovenlokale cultuurwerking</strong> die zullen gelden vanaf de indienronde van 15 november 2020 tot en met de indienronde van 15 mei 2025.&nbsp;\n\n<!-- components -->\n<!---->",
        "position": 1,
        "mandateeNames": null,
        "mandateeFirstNames": "Jan",
        "mandateeFamilyNames": "Jambon",
        "mandateeIds": "5fed907ee6670526694a070c",
        "mandateeTitles": "Minister-president van de Vlaamse Regering",
        "meetingDate": "2020-06-26T08:00:00Z",
        "meetingId": "5EF1A213AD269200080003B6",
        "meetingTypePosition": 4,
        "themeId": "5ae2b345-3a34-422c-9ee5-a90927fd2158",
        "agendaitemType": "Nota",
        "uuid": "5EF1ADDBAD26920008000518",
        "uri": "http://themis.vlaanderen.be/id/resource/ca3fa190-4928-11ec-94bb-99a9d1e168fe"
    }
}