{
    "type": "news-item",
    "id": "617940D7364ED90008000634",
    "attributes": {
        "title": "Vlaamse sociale bescherming: wijzigingsbesluit werkingssubsidie zorgkassen",
        "alternativeTitle": "Voorontwerp van besluit van de Vlaamse Regering tot wijziging van het besluit van de Vlaamse Regering van 14 oktober 2016 houdende de voorwaarden van de vaststelling, de uitbetaling en de terugvordering van de subsidies van de zorgkassen in het kader van de Vlaamse sociale bescherming",
        "htmlContent": "Het decreet met de regelgeving rond de Vlaamse sociale bescherming voorziet de integratie van een aantal oude RIZIV-sectoren in de Vlaamse sociale bescherming. In een eerste fase zijn dat de revalidatieziekenhuizen en het multidisciplinair overleg. Om&nbsp;deze integratie mogelijk te maken, <strong>wijzigt de Vlaamse Regering principieel&nbsp;het besluit met de voorwaarden voor de vaststelling, de uitbetaling en de terugvordering van de subsidies van de zorgkassen.</strong> Het zijn immers de zorgkassen die vanaf januari 2022 zorgen voor de uitbetaling van de tegemoetkomingen aan de revalidatieziekenhuizen en de uitbetaling van het multidisciplinair overleg. De werkingssubsidies van de zorgkassen worden ook aangepast aan de uitbreiding van hun taken. Door de verregaande digitalisering besliste de Vlaamse Regering wel om de recurrente werkingssubsidies van de zorgkassen bij de begrotingsopmaak 2022 met 1,2 miljoen euro te verminderen.&nbsp;Over dit wijzigingsbesluit wordt het advies ingewonnen van de Raad van State.&nbsp;",
        "position": 30,
        "mandateeNames": null,
        "mandateeFirstNames": "Wouter",
        "mandateeFamilyNames": "Beke",
        "mandateeIds": "74cf5db5-8b6c-442e-baf4-97fbc896f986",
        "mandateeTitles": "Vlaams minister van Welzijn, Volksgezondheid, Gezin en Armoedebestrijding",
        "meetingDate": "2021-10-29T09:15:00Z",
        "meetingId": "6176740D364ED90008000389",
        "meetingTypePosition": 4,
        "themeId": "4a0bb077-a416-4e4d-96ce-b2e89cec0a47",
        "agendaitemType": "Nota",
        "uuid": "617940D7364ED90008000634",
        "uri": "http://themis.vlaanderen.be/id/nieuwsbrief-info/617940D7364ED90008000634"
    }
}