{
    "type": "news-item",
    "id": "5ED0C867FE23BF000800039C",
    "attributes": {
        "title": "Raad van bestuur Vlaams Agentschap voor Internationaal Ondernemen (FIT): benoeming leden",
        "alternativeTitle": "Ontwerpbesluit van de Vlaamse Regering tot benoeming van de leden in de raad van bestuur van en regeringscommissaris bij het Vlaams Agentschap voor Internationaal Ondernemen",
        "htmlContent": "              <!---->\n\n De Vlaamse Regering <strong>benoemt&nbsp;de leden van de raad van bestuur en een regeringscommissaris bij het Vlaams Agentschap voor Internationaal Ondernemen (FIT) </strong>voor een hernieuwbare termijn van vijf jaar.&nbsp;\n\n<!-- components -->\n<!---->",
        "position": 4,
        "mandateeNames": null,
        "mandateeFirstNames": "Jan",
        "mandateeFamilyNames": "Jambon",
        "mandateeIds": "5fed907ee6670526694a070c",
        "mandateeTitles": "Minister-president van de Vlaamse Regering",
        "meetingDate": "2020-05-29T08:00:00Z",
        "meetingId": "5ECCB0BCFE23BF0008000002",
        "meetingTypePosition": 4,
        "themeId": [
            "9d82e85b-a02c-4bf0-b324-1eb0b5e81042",
            "abebd345-3650-400c-b317-9a8da2760f21"
        ],
        "agendaitemType": "Nota",
        "uuid": "5ED0C867FE23BF000800039C",
        "uri": "http://themis.vlaanderen.be/id/resource/3708e7a0-4929-11ec-94bb-99a9d1e168fe"
    }
}