{
    "type": "news-item",
    "id": "5EBD695FFE23BF0008000427",
    "attributes": {
        "title": "Stilligvergoeding visserij in kader van coronacrisis",
        "alternativeTitle": "Ontwerpbesluit van de Vlaamse Regering tot wijziging van het besluit van de Vlaamse Regering van 5 februari 2016 houdende vaststelling van de werking en het beheer van het Financieringsinstrument voor de Vlaamse visserij- en aquacultuursector (FIVA) en de verrichtingen die voor steun in aanmerking komen",
        "htmlContent": "                                          <!---->\n\n De maatregelen ten gevolge van de&nbsp;Covid-19 pandemie&nbsp;hebben ook verstrekkende gevolgen voor de reguliere werking en dienstverlening van de <strong>visserijsector</strong>. Doordat horeca en markten gesloten zijn en ook export voor een groot stuk is weggevallen, is de vraag naar vis en de prijs op de vismarkt fors&nbsp;gedaald. <strong>Europese regelgeving</strong> voorziet daarom de mogelijkheid een <strong>vergoeding te verlenen bij tijdelijke stopzetting van visserijactiviteiten</strong> in de periode tussen 1 februari en 31 december 2020. De Vlaamse Regering <strong>implementeert nu deze regeling in Vlaamse regelgeving. Ze wijzigt daarvoor het besluit over de werking en het beheer van&nbsp;het Financieringsinstrument voor de Vlaamse visserij- en aquacultuursector (FIVA).</strong>\n\n<!-- components -->\n<!---->\n\n&nbsp;\n\n<!-- components -->\n<!---->\n\n&nbsp;\n\n<!-- components -->\n<!---->",
        "position": 7,
        "mandateeNames": null,
        "mandateeFirstNames": "Hilde",
        "mandateeFamilyNames": "Crevits",
        "mandateeIds": "5fed907ee6670526694a070d",
        "mandateeTitles": "Vlaams minister van Economie, Innovatie, Werk, Sociale economie en Landbouw",
        "meetingDate": "2020-05-15T08:00:00Z",
        "meetingId": "5EBA486FFE23BF0008000185",
        "meetingTypePosition": 4,
        "themeId": "872c910d-dd86-46b4-a3b0-0ff45df32702",
        "agendaitemType": "Nota",
        "uuid": "5EBD695FFE23BF0008000427",
        "uri": "http://themis.vlaanderen.be/id/resource/65050f80-4929-11ec-94bb-99a9d1e168fe"
    }
}