{
    "type": "news-item",
    "id": "649AB61B2D77B42474D4E85E",
    "attributes": {
        "title": "Werkingssubsidies sectorconvenants 2023-2025",
        "alternativeTitle": "A.\t38 ontwerpen van sectorconvenant 2023-2025\nB.\t29 ontwerpbesluiten van de Vlaamse Regering houdende toekenning van een subsidie en een toelage",
        "htmlContent": "<p data-indentation-level=\"0\">De Vlaamse Regering <strong>keurt de werkingssubsidie goed voor 38 sectorconvenants 2023-2025</strong> <strong>voor de periode van 1 juli 2023 tot en met 30 juni 2025</strong>, voor de volgende sectoren: APCB; de Audiovisuele sector en Filmproductie; de Autosector; Banken, de Begrafenissector; Betonindustrie;  Binnenvaart; Bouw, Handel in brandstoffen; de sector Detailhandel; Diamant; erkende ondernemingen die buurtwerken of -diensten leveren; Elektriciens: installatie en distributie; de Grafische sector; de Groene sectoren, de Horecasector; Stoffering en houtbewerking; Houtnijverheid, zagerijen en houthandel; het paritair comit\u00e9 voor de bedienden uit de internationale handel, het vervoer en de logistiek; Kappers, fitness en schoonheidszorgen; Kleding en confectie;  Lokale besturen; Metaal en Technologische industrie; Papier- en kartonverwerkende nijverheid en Papierproductie; Private autobus- en autocarbedrijven; Chemie, Kunststoffen en Life Sciences; Social profit; Taxiondernemingen en diensten voor het verhuur van voertuigen met bestuurder; Textiel; Textielverzorging; Transport en Logistiek en Grondafhandeling op luchthavens; Uitzendarbeid; Vastgoed; Verhuisondernemingen, meubelbewaring en aanverwante activiteiten; Vermakelijkheidsbedrijf; Voedingshandel; Voedingsnijverheid; Vrije beroepen en Zelfstandige kleinhandel. Sectorconvenanten beogen het ondersteunen van duurzame loopbanen, individuen en organisaties met oog op veerkracht bij transities en de verhoging van de werkzaamheidsgraad. De Vlaamse Regering keurt tegelijk een toelage goed van 260.000 euro aan de SERV voor de intersectorale ondersteuning van de sectorconvenants 2023-2025 voor de periode van 1 juli 2023 tot en met 30 juni 2024.</p>",
        "position": 46,
        "mandateeNames": null,
        "mandateeFirstNames": "Jo",
        "mandateeFamilyNames": "Brouns",
        "mandateeIds": "f7fe3320-7c15-4322-b907-02571d3dfe6e",
        "mandateeTitles": "Vlaams minister van Economie, Innovatie, Werk, Sociale Economie en Landbouw",
        "meetingDate": "2023-06-30T08:00:00Z",
        "meetingId": "649998A72D77B42474D4E38E",
        "meetingTypePosition": 4,
        "themeId": "faf802ff-bca7-4419-acc0-d84937e5bcd4",
        "agendaitemType": "Nota",
        "uuid": "649AB61B2D77B42474D4E85E",
        "uri": "http://themis.vlaanderen.be/id/nieuwsbericht/649AB61B2D77B42474D4E85E"
    }
}