{
    "type": "news-item",
    "id": "651D502E7FDB1A5D07827AF2",
    "attributes": {
        "title": "Steun voor opstart van of omschakeling naar een toekomstgerichte duurzame ondernemingsstrategie op een landbouwbedrijf",
        "alternativeTitle": "Ontwerpbesluit van de Vlaamse Regering over de steun voor de opstart van of de omschakeling naar een toekomstgerichte duurzame ondernemingsstrategie op een landbouwbedrijf",
        "htmlContent": "<p data-indentation-level=\"0\">Sinds 1 januari 2023 is het nieuw Gemeenschappelijk Landbouwbeleid (GLB) van toepassing. Artikel 75 van de Europese GLB- verordening bepaalt dat lidstaten steun kunnen verstrekken voor het opstarten van plattelandsbedrijven die verband houden met land- of bosbouw, met inbegrip van de vestiging van nieuwe landbouwers, of de diversificatie van inkomens van landbouwhuishoudens naar niet-landbouwgerelateerde activiteiten. De Vlaamse Regering keurt daarom, na advies van de VTC, de GBA en de Raad van State, definitief een steunmaatregel goed die voorziet in de <strong>toekenning van steun voor investeringen voor de opstart van of omschakeling naar een toekomstgerichte duurzame ondernemingsstrategie op een landbouwbedrijf</strong>. Deze steunmaatregel beoogt het ondersteunen van bedrijven voor het implementeren van een vernieuwde niet-gangbare bedrijfsstrategie op maat van het bedrijf, die gepaard gaat met inkomens- en succesrisico\u2019s in de eerste jaren van de implementatie. De vernieuwde bedrijfsstrategie moet hun bedrijf veerkrachtig en toekomstgericht maken, de economische leefbaarheid van het bedrijf waarborgen en bijdragen aan het leveren van belangrijke diensten aan de samenleving. Voor deze steunmaatregel kan een beroep gedaan worden op Europese cofinanciering. Het Vlaamse luik wordt gefinancierd vanuit het Vlaams Landbouwinvesteringsfonds (VLIF). Vanuit het VLIF wordt voor deze maatregel <strong>5,15 miljoen euro voor de periode 2023-2027 </strong>voorzien.</p>",
        "position": 44,
        "mandateeNames": null,
        "mandateeFirstNames": "Jo",
        "mandateeFamilyNames": "Brouns",
        "mandateeIds": "f7fe3320-7c15-4322-b907-02571d3dfe6e",
        "mandateeTitles": "Vlaams minister van Economie, Innovatie, Werk, Sociale Economie en Landbouw",
        "meetingDate": "2023-10-06T08:00:00Z",
        "meetingId": "651AC01D51A2D987E57E2FDA",
        "meetingTypePosition": 4,
        "themeId": "872c910d-dd86-46b4-a3b0-0ff45df32702",
        "agendaitemType": "Nota",
        "uuid": "651D502E7FDB1A5D07827AF2",
        "uri": "http://themis.vlaanderen.be/id/nieuwsbericht/651D502E7FDB1A5D07827AF2"
    }
}