{
    "type": "news-item",
    "id": "5ECCC0A0FE23BF00080000CF",
    "attributes": {
        "title": "Samenwerkingsakkoord hervorming adoptie: voorontwerp instemmingsdecreet",
        "alternativeTitle": null,
        "htmlContent": "                                                                      <p>Op 6 maart 2020 keurde de&nbsp;Vlaamse Regering het gewijzigde <strong>samenwerkingsakkoord </strong>goed t<strong>ussen de Federale Staat, de Vlaamse Gemeenschap, de Franse Gemeenschap, de Duitstalige Gemeenschap en de Gemeenschappelijke Gemeenschapscommissie over de tenuitvoerlegging van de wet tot hervorming van de adoptie</strong>. Na advies van de Raad van State hecht ze nu&nbsp;haar <strong>definitieve&nbsp;goedkeuring aan het ontwerpdecreet dat met dit samenwerkingsakkoord instemt</strong>. Het ontwerp van instemmingsdecreet wordt nu ingediend bij het Vlaams Parlement.&nbsp;</p>\n\n\n&nbsp;\n\n<!-- components -->\n<!---->\n\n&nbsp;\n\n<!-- components -->\n<!---->\n\n&nbsp;\n\n<!-- components -->\n<!---->\n\n&nbsp;\n\n<!-- components -->\n<!---->\n\n&nbsp;\n\n<!-- components -->\n<!---->",
        "position": 34,
        "mandateeNames": null,
        "mandateeFirstNames": "Wouter",
        "mandateeFamilyNames": "Beke",
        "mandateeIds": "5fed907ee6670526694a0719",
        "mandateeTitles": "Vlaams minister van Welzijn, Volksgezondheid, Gezin en Armoedebestrijding",
        "meetingDate": "2020-05-29T08:00:00Z",
        "meetingId": "5ECCB0BCFE23BF0008000002",
        "meetingTypePosition": 4,
        "themeId": [
            "30354d68-91c8-47b0-b5ba-6418d261f642",
            "0cc58cdc-dcf4-4d6c-bc9e-27ea721baf25",
            "4a0bb077-a416-4e4d-96ce-b2e89cec0a47"
        ],
        "agendaitemType": "Nota",
        "uuid": "5ECCC0A0FE23BF00080000CF",
        "uri": "http://themis.vlaanderen.be/id/resource/388aa5a0-4929-11ec-94bb-99a9d1e168fe"
    }
}