{
    "type": "news-item",
    "id": "5EAFE0ED720F380008000281",
    "attributes": {
        "title": "Begrotingscontrole 2020: ontwerp programmadecreet bij de aanpassing van de begroting 2020",
        "alternativeTitle": "Voorontwerp van programmadecreet bij de aanpassing van de begroting 2020\n",
        "htmlContent": "                            <!----> Na adviezen van de Raad van State en van diverse Strategische Adviesraden hecht de Vlaamse Regering haar <strong>definitieve goedkeuring</strong> aan&nbsp;het <strong>ontwerp van programmadecreet bij&nbsp;de aanpassing&nbsp;van de begroting 2020 en aan de bijhorende Memorie van Toelichting</strong>. Dit ontwerpdecreet wordt nu ingediend bij het Vlaams Parlement.<!-- components -->\n<!---->",
        "position": 5,
        "mandateeNames": null,
        "mandateeFirstNames": "Matthias",
        "mandateeFamilyNames": "Diependaele",
        "mandateeIds": "5fed907ee6670526694a071b",
        "mandateeTitles": "Vlaams minister van Financi\u00ebn en Begroting, Wonen en Onroerend Erfgoed",
        "meetingDate": "2020-05-04T09:00:00Z",
        "meetingId": "5EAFDF60720F38000800025F",
        "meetingTypePosition": 3,
        "themeId": "6053f77e-09d3-4d08-8b1e-1fc5f34f3667",
        "agendaitemType": "Nota",
        "uuid": "5EAFE0ED720F380008000281",
        "uri": "http://themis.vlaanderen.be/id/resource/b3e5ee80-4929-11ec-94bb-99a9d1e168fe"
    }
}