{
    "type": "news-item",
    "id": "5FD898A96B34EF0008000A21",
    "attributes": {
        "title": "Maatregelen cultuur- en jeugdinfrastructuur en operationalisering Departement Cultuur, Jeugd en Media: wijzigingsbesluit",
        "alternativeTitle": "Voorontwerp van besluit van de Vlaamse Regering houdende wijziging van diverse besluiten, wat betreft maatregelen voor cultuur- en jeugdinfrastructuur en de operationalisering van het Departement Cultuur, Jeugd en Media, en tot opheffing van het besluit van de Vlaamse regering van 2 februari 1999 tot regeling van het beheer en de werking van het Fonds culturele infrastructuur",
        "htmlContent": "Omdat bij het&nbsp;Programmadecreet het <strong>Fonds Culturele Infrastructuur opgeheven</strong> wordt,&nbsp;de taken van het&nbsp;fonds overgeheveld worden naar de Vlaamse Gemeenschap en&nbsp;een <strong>begrotingsfonds</strong> wordt&nbsp;<strong>opgericht</strong>, <strong>past de Vlaamse Regering principieel een aantal uitvoeringsbesluiten aan</strong>. Tegelijkertijd wordt de wetgeving overheidsopdrachten van toepassing verklaard op alle werken, diensten en leveringen waarvoor een investeringssubsidie wordt verleend en worden de taken van het Departement Cultuur, Jeugd en Media geactualiseerd. Over dit wijzigingsbesluit wordt het&nbsp;advies ingewonnen&nbsp;van de Raad van State.",
        "position": 13,
        "mandateeNames": null,
        "mandateeFirstNames": [
            "Jan",
            "Benjamin"
        ],
        "mandateeFamilyNames": [
            "Jambon",
            "Dalle"
        ],
        "mandateeIds": [
            "5fed907ee6670526694a070c",
            "5fed907ee6670526694a071e"
        ],
        "mandateeTitles": [
            "Minister-president van de Vlaamse Regering",
            "Vlaams minister van Brussel, Jeugd en Media"
        ],
        "meetingDate": "2020-12-18T09:00:00Z",
        "meetingId": "5FD7A4CF6B34EF0008000224",
        "meetingTypePosition": 4,
        "themeId": [
            "5ae2b345-3a34-422c-9ee5-a90927fd2158",
            "6053f77e-09d3-4d08-8b1e-1fc5f34f3667",
            "34654906-74bd-4a69-9f93-0971f263cca3",
            "12f19487-9fc6-4c02-afc3-0015b1127144"
        ],
        "agendaitemType": "Nota",
        "uuid": "5FD898A96B34EF0008000A21",
        "uri": "http://themis.vlaanderen.be/id/resource/a9591d10-4925-11ec-94bb-99a9d1e168fe"
    }
}