{
    "type": "news-item",
    "id": "5DEF63B45084E70008000460",
    "attributes": {
        "title": "Herverdeling provisie: Hermesfonds innovatieclusters",
        "alternativeTitle": "Ontwerpbesluit van de Vlaamse Regering over de herverdeling van begrotingsartikelen van de algemene uitgavenbegroting van de Vlaamse Gemeenschap voor het begrotingsjaar 2019 in het kader van de innovatiesteun",
        "htmlContent": "                            <!---->\n\n In het kader van een <strong>bijkomende ondersteuning aan de innovatieclusters</strong> beslist de Vlaamse Regering tot <strong>herverdeling </strong>van begrotingsartikelen voor een bedrag van <strong>3,066 miljoen euro</strong> vanuit EWI&nbsp;<strong>naar het Fonds voor Flankerend Economisch en Innovatiebeleid (Hermesfonds)</strong>.\n\n<!-- components -->\n<!---->\n\n&nbsp;\n\n<!-- components -->\n<!---->",
        "position": 16,
        "mandateeNames": null,
        "mandateeFirstNames": "Hilde",
        "mandateeFamilyNames": "Crevits",
        "mandateeIds": "5fed907ee6670526694a070d",
        "mandateeTitles": "Vlaams minister van Economie, Innovatie, Werk, Sociale economie en Landbouw",
        "meetingDate": "2019-12-13T09:00:00Z",
        "meetingId": "5DEE61125084E700080001A8",
        "meetingTypePosition": 4,
        "themeId": [
            "faf802ff-bca7-4419-acc0-d84937e5bcd4",
            "c8a94efe-10a8-4f5f-a77a-2ca188dc7b51"
        ],
        "agendaitemType": "Nota",
        "uuid": "5DEF63B45084E70008000460",
        "uri": "http://themis.vlaanderen.be/id/resource/9669f2f0-492b-11ec-94bb-99a9d1e168fe"
    }
}