{
    "type": "news-item",
    "id": "64A2F3D72D77B42474D4F1C2",
    "attributes": {
        "title": "Het Co\u00f6rdinatieplatform Stand van de Rand: projectmonitoringsfiches",
        "alternativeTitle": null,
        "htmlContent": null,
        "position": 94,
        "mandateeNames": null,
        "mandateeFirstNames": "Ben",
        "mandateeFamilyNames": "Weyts",
        "mandateeIds": "d283fd40-f781-4300-a913-60658e2aec85",
        "mandateeTitles": "Vlaams minister van Onderwijs, Sport, Dierenwelzijn en Vlaamse Rand",
        "meetingDate": "2023-07-07T09:00:00Z",
        "meetingId": "64A2DFCF2D77B42474D4F019",
        "meetingTypePosition": 4,
        "themeId": null,
        "agendaitemType": "Mededeling",
        "uuid": "64A2F3D72D77B42474D4F1C2",
        "uri": "http://themis.vlaanderen.be/id/nieuwsbericht/64A2F3D72D77B42474D4F1C2"
    }
}