{
    "type": "news-item",
    "id": "61B8B627364ED900090015B4",
    "attributes": {
        "title": "Verzameldecreet maatregelen onderwijs",
        "alternativeTitle": "Voorontwerp van decreet over diverse maatregelen voor het onderwijs",
        "htmlContent": "De Vlaamse Regering <strong>hecht haar principi\u00eble goedkeuring aan het voorontwerp van decreet&nbsp;dat een aantal bestaande niveau- en themadecreten over onderwijs verbetert en aanvult.</strong> Over dit voorontwerp van decreet wordt het advies ingewonnen van de VLOR en van de SERV. Het wordt ook voor onderhandelingen voorgelegd aan de sociale partners en gaat daarna voor advies naar de Raad van State.",
        "position": 84,
        "mandateeNames": null,
        "mandateeFirstNames": "Ben",
        "mandateeFamilyNames": "Weyts",
        "mandateeIds": "d437d986-09de-4b46-8fce-f6ca4389f492",
        "mandateeTitles": "Vlaams minister van Onderwijs, Sport, Dierenwelzijn en Vlaamse Rand",
        "meetingDate": "2021-12-17T09:00:00Z",
        "meetingId": "61B760B9364ED900090008A6",
        "meetingTypePosition": 4,
        "themeId": "ee9bda4a-f54a-41d5-be2f-9d45781623be",
        "agendaitemType": "Nota",
        "uuid": "61B8B627364ED900090015B4",
        "uri": "http://themis.vlaanderen.be/id/nieuwsbrief-info/61B8B627364ED900090015B4"
    }
}