{
    "type": "news-item",
    "id": "65563D058265E66451D4CBEA",
    "attributes": {
        "title": "Cofinanciering vanuit het Vlaams Klimaatfonds ter ondersteuning van publieke laadinfrastructuur voor elektrische wagens op privaat domein",
        "alternativeTitle": null,
        "htmlContent": "<p data-indentation-level=\"0\">De Vlaamse Regering lanceerde op 3 oktober 2023 een <strong>projectoproep voor de financi\u00eble ondersteuning van publieke laadinfrastructuur op privaat domein</strong>, om mee de omschakeling naar elektrische voertuigen te bespoedigen. Ze keurt in dit verband nu de <strong>reservering goed van het voorgesteld budget van 2,897 miljoen euro</strong> van het Vlaams Klimaatfonds.</p>",
        "position": 36,
        "mandateeNames": null,
        "mandateeFirstNames": "Lydia",
        "mandateeFamilyNames": "Peeters",
        "mandateeIds": "305a87c9-6806-42a0-81c9-f6a94c4e8464",
        "mandateeTitles": "Vlaams minister van Mobiliteit en Openbare Werken",
        "meetingDate": "2023-11-17T09:00:00Z",
        "meetingId": "655239658265E66451D4C5B1",
        "meetingTypePosition": 4,
        "themeId": "17ddaff0-b2e3-4f02-9157-76a1cf593a5b",
        "agendaitemType": "Nota",
        "uuid": "65563D058265E66451D4CBEA",
        "uri": "http://themis.vlaanderen.be/id/nieuwsbericht/65563D058265E66451D4CBEA"
    }
}